{
  "name": "@microsoft/azure-speech",
  "description": "Transcribe short audio, fast single files, or batch audio URLs with Azure AI Speech. Convert text or SSML to neural speech audio attachments, list available voices and base speech models, assess pronunciation on short audio, and manage text-independent speaker profiles for enrollment, verification, and identification.",
  "categories": ["apis-and-http-requests", "speech-recognition-and-synthesis"],
  "skills": [
    "transcribe audio to text",
    "synthesize speech from text",
    "fast transcribe audio files",
    "batch transcribe audio files",
    "identify and diarize speakers",
    "verify speaker identity",
    "assess pronunciation quality",
    "enroll speaker profiles",
    "identify spoken language"
  ],
  "logoUrl": "https://provider-logos.metorial-cdn.com/azure-speech.png"
}
